logging_utils-1.0.2.dist-info/DESCRIPTION.rst
logging_utils-1.0.2.dist-info/METADATA
logging_utils-1.0.2.dist-info/RECORD
logging_utils-1.0.2.dist-info/WHEEL
logging_utils-1.0.2.dist-info/metadata.json
logging_utils-1.0.2.dist-info/top_level.txt
loggingutils/__init__.py
loggingutils/handlers.py
