Metadata-Version: 2.0
Name: logging-utils
Version: 1.0.2
Summary: Additional utilities for Python logging.
Home-page: https://github.com/faeriol/LoggingUtils
Author: Max Paradis
Author-email: max@faeriol.me
License: UNKNOWN
Keywords: logging,utilities
Platform: UNKNOWN
Classifier: Environment :: Web Environment
Classifier: Intended Audience :: Developers
Classifier: License :: OSI Approved :: MIT License
Classifier: Programming Language :: Python :: 3
Classifier: Programming Language :: Python :: 3.5
